codegen/py.typed
codegen/git/__init__.pyi
codegen/git/local_repo_operator.pyi
codegen/git/repo_operator.pyi
codegen/git/schemas/config.pyi
codegen/git/schemas/enums.pyi
graph_sitter/__init__.pyi
graph_sitter/_proxy.pyi
graph_sitter/codemod.pyi
graph_sitter/constants.pyi
graph_sitter/enums.pyi
graph_sitter/exceptions.pyi
graph_sitter/perf.pyi
graph_sitter/py.typed
graph_sitter/secrets.pyi
graph_sitter/topological_sort.pyi
graph_sitter/tree_sitter_parser.pyi
graph_sitter/types.pyi
graph_sitter/utils.pyi
graph_sitter/writer_decorators.pyi
graph_sitter/ai/converters.pyi
graph_sitter/ai/helpers.pyi
graph_sitter/code_generation/__init__.pyi
graph_sitter/codebase/__init__.pyi
graph_sitter/codebase/codebase_ai.pyi
graph_sitter/codebase/codebase_graph.pyi
graph_sitter/codebase/config.pyi
graph_sitter/codebase/config_parser.pyi
graph_sitter/codebase/control_flow.pyi
graph_sitter/codebase/diff_lite.pyi
graph_sitter/codebase/range_index.pyi
graph_sitter/codebase/resolution_stack.pyi
graph_sitter/codebase/span.pyi
graph_sitter/codebase/transaction_manager.pyi
graph_sitter/codebase/transactions.pyi
graph_sitter/codebase/validation.pyi
graph_sitter/codebase/flagging/code_flag.pyi
graph_sitter/codebase/flagging/enums.pyi
graph_sitter/codebase/flagging/flags.pyi
graph_sitter/codebase/node_classes/node_classes.pyi
graph_sitter/codebase/node_classes/py_node_classes.pyi
graph_sitter/codebase/node_classes/ts_node_classes.pyi
graph_sitter/core/__init__.pyi
graph_sitter/core/assignment.pyi
graph_sitter/core/class_definition.pyi
graph_sitter/core/codebase.pyi
graph_sitter/core/directory.pyi
graph_sitter/core/export.pyi
graph_sitter/core/external_module.pyi
graph_sitter/core/file.pyi
graph_sitter/core/function.pyi
graph_sitter/core/import_resolution.pyi
graph_sitter/core/interface.pyi
graph_sitter/core/node_id_factory.pyi
graph_sitter/core/parser.pyi
graph_sitter/core/symbol.pyi
graph_sitter/core/symbol_group.pyi
graph_sitter/core/type_alias.pyi
graph_sitter/core/autocommit/__init__.pyi
graph_sitter_types-6.6.8.dist-info/METADATA
graph_sitter_types-6.6.8.dist-info/WHEEL
graph_sitter_types-6.6.8.dist-info/RECORD
